NumTextAlchemy/__init__.py
NumTextAlchemy/converter.py
NumTextAlchemy-0.1.2.dist-info/LICENSE
NumTextAlchemy-0.1.2.dist-info/METADATA
NumTextAlchemy-0.1.2.dist-info/WHEEL
NumTextAlchemy-0.1.2.dist-info/top_level.txt
NumTextAlchemy-0.1.2.dist-info/RECORD
