Metadata-Version: 2.1
Name: NumTextAlchemy
Version: 0.1.2
Summary: NumTextAlchemy is a Python library designed to convert extremely large numbers into their text representations and back to their numerical form.
Home-page: https://github.com/Srinath-N-Gudi/NumTextAlchemy
Author: Srinath Gudi
Author-email: srinathngudi11@gmail.com
License: MIT
Keywords: python,library,num2text,num2words,numbers,texts,words,conversion,alchemy,numtext
Classifier: Programming Language :: Python :: 3
Classifier: License :: OSI Approved :: MIT License
Classifier: Operating System :: OS Independent
Requires-Python: >=3.0
License-File: LICENSE
